brave/__init__.py
brave/async_brave.py
brave/client.py
brave/exceptions.py
brave/goggles/README.md
brave/goggles/__init__.py
brave/goggles/directory.py
brave/goggles/sample_goggle.goggle
brave/goggles/thought_leadership.goggle
brave/sync.py
brave/types/__init__.py
brave/types/image/__init__.py
brave/types/image/image_query.py
brave/types/image/image_result.py
brave/types/image/image_search_response.py
brave/types/image/properties.py
brave/types/not_implemented.py
brave/types/shared/__init__.py
brave/types/shared/meta_url.py
brave/types/shared/thumbnail.py
brave/types/web/answer.py
brave/types/web/article.py
brave/types/web/book.py
brave/types/web/button_result.py
brave/types/web/contact.py
brave/types/web/data_provider.py
brave/types/web/deep_result.py
brave/types/web/discussions.py
brave/types/web/faq.py
brave/types/web/image.py
brave/types/web/info_box.py
brave/types/web/knowledge_graph.py
brave/types/web/language.py
brave/types/web/location_result.py
brave/types/web/mixed_response.py
brave/types/web/movie_data.py
brave/types/web/news.py
brave/types/web/offer.py
brave/types/web/opening_hours.py
brave/types/web/person.py
brave/types/web/picture_results.py
brave/types/web/postal_address.py
brave/types/web/price.py
brave/types/web/product.py
brave/types/web/profile.py
brave/types/web/query.py
brave/types/web/rating.py
brave/types/web/result.py
brave/types/web/reviews.py
brave/types/web/search.py
brave/types/web/search_result.py
brave/types/web/unit.py
brave/types/web/url.py
brave/types/web/videos.py
brave/types/web/web_search_response.py
brave_search-0.1.7.dist-info/LICENSE.MD
brave_search-0.1.7.dist-info/METADATA
brave_search-0.1.7.dist-info/WHEEL
brave_search-0.1.7.dist-info/RECORD
