Metadata-Version: 2.1
Name: brave-search
Version: 0.1.7
Summary: Brave Search API wrapper
Home-page: https://github.com/kayvane1/brave-api
Keywords: search,brave,api
Author: Kayvane Shakerifar
Requires-Python: >=3.8,<4.0
Classifier: Programming Language :: Python :: 3
Classifier: Programming Language :: Python :: 3.8
Classifier: Programming Language :: Python :: 3.9
Classifier: Programming Language :: Python :: 3.10
Classifier: Programming Language :: Python :: 3.11
Requires-Dist: httpx (>=0.25.2,<0.26.0)
Requires-Dist: numpy (>=1.24.4,<2.0.0)
Requires-Dist: pydantic (>=2.5.2,<3.0.0)
Requires-Dist: pytest-asyncio (>=0.23.2,<0.24.0)
Requires-Dist: requests (>=2.26.0,<3.0.0)
Requires-Dist: tenacity (>=8.2.3,<9.0.0)
Project-URL: Repository, https://github.com/kayvane1/brave-api
